hufflepuff/__init__.py
hufflepuff/cli.py
hufflepuff/comms.py
hufflepuff/minigraph.py
hufflepuff/search.py
hufflepuff/strategies.py
hufflepuff-1.4.dist-info/LICENSE
hufflepuff-1.4.dist-info/METADATA
hufflepuff-1.4.dist-info/WHEEL
hufflepuff-1.4.dist-info/entry_points.txt
hufflepuff-1.4.dist-info/top_level.txt
hufflepuff-1.4.dist-info/RECORD
