Metadata-Version: 2.1
Name: hufflepuff
Version: 1.4
Summary: Hufflepuffs are particularly good finders.
Home-page: https://hg.flowblok.id.au/hufflepuff
Author: Peter Ward
Author-email: peteraward@gmail.com
License: UNKNOWN
Platform: UNKNOWN
Requires-Dist: six
